jupyter_gcp/__init__.py
jupyter_gcp/_version.py
jupyter_gcp/handlers.py
jupyter_gcp/tests/__init__.py
jupyter_gcp/tests/test_handlers.py
jupyter_gcp-0.0.2.data/data/etc/jupyter/jupyter_notebook_config.d/jupyter_gcp.json
jupyter_gcp-0.0.2.data/data/etc/jupyter/jupyter_server_config.d/jupyter_gcp.json
jupyter_gcp-0.0.2.data/data/share/jupyter/labextensions/@datalayer/jupyter-gcp/build_log.json
jupyter_gcp-0.0.2.data/data/share/jupyter/labextensions/@datalayer/jupyter-gcp/package.json
jupyter_gcp-0.0.2.data/data/share/jupyter/labextensions/@datalayer/jupyter-gcp/schemas/@datalayer/jupyter-gcp/package.json.orig
jupyter_gcp-0.0.2.data/data/share/jupyter/labextensions/@datalayer/jupyter-gcp/schemas/@datalayer/jupyter-gcp/plugin.json
jupyter_gcp-0.0.2.data/data/share/jupyter/labextensions/@datalayer/jupyter-gcp/static/design_icons_lib_index_js.f53ac6fd4bc34fdbab4e.js
jupyter_gcp-0.0.2.data/data/share/jupyter/labextensions/@datalayer/jupyter-gcp/static/design_icons_lib_index_js.f53ac6fd4bc34fdbab4e.js.map
jupyter_gcp-0.0.2.data/data/share/jupyter/labextensions/@datalayer/jupyter-gcp/static/lib_index_js.3df309d1051a3be28d32.js
jupyter_gcp-0.0.2.data/data/share/jupyter/labextensions/@datalayer/jupyter-gcp/static/lib_index_js.3df309d1051a3be28d32.js.map
jupyter_gcp-0.0.2.data/data/share/jupyter/labextensions/@datalayer/jupyter-gcp/static/remoteEntry.d4eced3f97ddd730c08a.js
jupyter_gcp-0.0.2.data/data/share/jupyter/labextensions/@datalayer/jupyter-gcp/static/remoteEntry.d4eced3f97ddd730c08a.js.map
jupyter_gcp-0.0.2.data/data/share/jupyter/labextensions/@datalayer/jupyter-gcp/static/style.js
jupyter_gcp-0.0.2.data/data/share/jupyter/labextensions/@datalayer/jupyter-gcp/static/style_index_js.4a2ee559ce41a82a9e25.js
jupyter_gcp-0.0.2.data/data/share/jupyter/labextensions/@datalayer/jupyter-gcp/static/style_index_js.4a2ee559ce41a82a9e25.js.map
jupyter_gcp-0.0.2.dist-info/METADATA
jupyter_gcp-0.0.2.dist-info/WHEEL
jupyter_gcp-0.0.2.dist-info/licenses/LICENSE
jupyter_gcp-0.0.2.dist-info/RECORD
